config_modules_vmware/__init__.py
config_modules_vmware/log_config.yml
config_modules_vmware/controllers/__init__.py
config_modules_vmware/controllers/base_controller.py
config_modules_vmware/controllers/esxi/__init__.py
config_modules_vmware/controllers/esxi/account_unlock_time_interval.py
config_modules_vmware/controllers/esxi/ad_esx_admin_group_config.py
config_modules_vmware/controllers/esxi/bridge_protocol_data_unit_filter.py
config_modules_vmware/controllers/esxi/cim_service_policy.py
config_modules_vmware/controllers/esxi/cluster_config.py
config_modules_vmware/controllers/esxi/dcui_idle_timeout.py
config_modules_vmware/controllers/esxi/dcui_login_banner.py
config_modules_vmware/controllers/esxi/dv_filter_bind_ip_config.py
config_modules_vmware/controllers/esxi/firewall_default_action_incoming.py
config_modules_vmware/controllers/esxi/firewall_default_action_outgoing.py
config_modules_vmware/controllers/esxi/firewall_rulesets_config.py
config_modules_vmware/controllers/esxi/host_client_session_idle_timeout.py
config_modules_vmware/controllers/esxi/hostd_log_level.py
config_modules_vmware/controllers/esxi/hyperthread_warning_policy.py
config_modules_vmware/controllers/esxi/image_profile_acceptance_level.py
config_modules_vmware/controllers/esxi/interactive_shell_idle_timeout.py
config_modules_vmware/controllers/esxi/lockdown_dcui_access_users.py
config_modules_vmware/controllers/esxi/lockdown_mode_config.py
config_modules_vmware/controllers/esxi/lockdown_mode_exception_users.py
config_modules_vmware/controllers/esxi/log_location_config.py
config_modules_vmware/controllers/esxi/managed_object_browser.py
config_modules_vmware/controllers/esxi/max_failed_login_attempts.py
config_modules_vmware/controllers/esxi/mem_share_force_salting_config.py
config_modules_vmware/controllers/esxi/ntp_config.py
config_modules_vmware/controllers/esxi/ntp_service_config.py
config_modules_vmware/controllers/esxi/ntp_service_startup_policy.py
config_modules_vmware-0.16.0.5.dist-info/licenses/LICENSE.txt
config_modules_vmware-0.16.0.5.dist-info/METADATA
config_modules_vmware-0.16.0.5.dist-info/WHEEL
config_modules_vmware-0.16.0.5.dist-info/entry_points.txt
config_modules_vmware-0.16.0.5.dist-info/top_level.txt
config_modules_vmware-0.16.0.5.dist-info/RECORD
