Metadata-Version: 2.4
Name: config_modules_vmware
Version: 0.16.0.5
Summary: VMware Unified Config Modules
Home-page: https://github.com/vmware/vmware-config-modules
Author: Broadcom
License: BSD-2-Clause+Patent
Project-URL: Issues, https://github.com/vmware/vmware-config-modules/issues
Project-URL: Changelog, https://github.com/vmware/vmware-config-modules/blob/master/CHANGELOG.md
Classifier: Programming Language :: Python :: 3
Classifier: Operating System :: OS Independent
Requires-Python: >=3.9
License-File: LICENSE.txt
Requires-Dist: pyVmomi==8.0.2.0.1
Requires-Dist: requests>=2.31.0
Requires-Dist: pyOpenSSL<=24.0.0,>=23.2.0
Requires-Dist: lxml<=5.2.2,>=4.9.1
Requires-Dist: jsonschema~=4.17.3
Requires-Dist: urllib3<2.0.0,>=1.26.6
Requires-Dist: beautifulsoup4>=4.12.3
Provides-Extra: api
Requires-Dist: fastapi~=0.114.0; python_version >= "3.8" and extra == "api"
Requires-Dist: fastapi~=0.103.2; python_version <= "3.7" and extra == "api"
Requires-Dist: uvicorn[standard]~=0.30.6; python_version >= "3.8" and extra == "api"
Requires-Dist: uvicorn[standard]~=0.22.0; python_version <= "3.7" and extra == "api"
Requires-Dist: gunicorn~=23.0.0; extra == "api"
Requires-Dist: pydantic~=2.9.0; python_version >= "3.8" and extra == "api"
Requires-Dist: pydantic~=2.5.3; python_version <= "3.7" and extra == "api"
Requires-Dist: pyyaml~=6.0.1; extra == "api"
Provides-Extra: salt
Requires-Dist: salt>=3006; extra == "salt"
Requires-Dist: looseversion; extra == "salt"
Dynamic: author
Dynamic: description
Dynamic: description-content-type
Dynamic: license-file
Dynamic: provides-extra
Dynamic: requires-dist
Dynamic: requires-python
Dynamic: summary
